PyCHAS/pychas.py
PyCHAS-1.0.2.dist-info/LICENSE
PyCHAS-1.0.2.dist-info/METADATA
PyCHAS-1.0.2.dist-info/WHEEL
PyCHAS-1.0.2.dist-info/entry_points.txt
PyCHAS-1.0.2.dist-info/top_level.txt
PyCHAS-1.0.2.dist-info/RECORD
