Metadata-Version: 2.1
Name: PyCHAS
Version: 1.0.2
Summary: Python C/C++ header amalgamation script
Home-page: https://notokay.dev/
Author: NotOkay
Author-email: Kara <contact@notokay.dev>
License: MIT
Project-URL: Source, https://github.com/EinKara/PyCHAS/
Project-URL: Sponsor, https://github.com/sponsors/EinKara/
Classifier: Intended Audience :: Developers
Classifier: License :: OSI Approved :: BSD License
Classifier: Natural Language :: English
Classifier: Operating System :: MacOS :: MacOS X
Classifier: Operating System :: POSIX
Classifier: Operating System :: POSIX :: BSD
Classifier: Operating System :: POSIX :: Linux
Classifier: Operating System :: Microsoft :: Windows
Classifier: Programming Language :: Python
Classifier: Programming Language :: Python :: 3
Classifier: Programming Language :: Python :: 3 :: Only
Classifier: Programming Language :: Python :: 3.7
Classifier: Programming Language :: Python :: 3.8
Classifier: Programming Language :: Python :: 3.9
Classifier: Programming Language :: Python :: 3.10
Requires-Python: >=3.7
License-File: LICENSE
